ZDTA/__common.py
ZDTA/__init__.py
ZDTA/__service_config.py
ZDTA/can_sim.py
ZDTA/klemmen.py
zdta-1.1.0.dist-info/LICENSE
zdta-1.1.0.dist-info/METADATA
zdta-1.1.0.dist-info/WHEEL
zdta-1.1.0.dist-info/top_level.txt
zdta-1.1.0.dist-info/RECORD
