Metadata-Version: 2.1
Name: zdta
Version: 1.1.0
Summary: testautomation
Author: zd_automotive
Classifier: Programming Language :: Python :: 3
Classifier: License :: OSI Approved :: MIT License
Classifier: Operating System :: OS Independent
Requires-Python: >=3.10
License-File: LICENSE
Requires-Dist: pillow
